{
  "header": {
    "title": "Cho Thuê Nhà Nguyên Căn, Giá Rẻ, Chính Chủ, Mới Nhất 2023",
    "description": "Cho thuê nhà nguyên căn - Kênh đăng tin cho thuê nhà số 1: giá rẻ, chính chủ, miễn trung gian, đầy đủ tiện nghi, mức giá, diện tích cho thuê khác nhau."
  },
  "body": [
    {
      "images": [
        "https://pt123.cdn.static123.com/images/thumbs/900x600/fit/2023/05/13/a66c9d81-52f4-469b-aa42-ff8287925372_1683914543.jpg",
        "https://pt123.cdn.static123.com/images/thumbs/900x600/fit/2023/05/13/cc1a516e-65c0-43c4-aac8-8d9cc533caf7_1683914537.jpg",
        "https://pt123.cdn.static123.com/images/thumbs/900x600/fit/2023/05/13/8ca3694b-70a0-426f-b5a6-7d6eee70f036_1683914538.jpg",
        "https://pt123.cdn.static123.com/images/thumbs/900x600/fit/2023/05/13/a823bb3b-91fa-443c-b1e9-f2cac139ed24_1683914542.jpg",
        "https://pt123.cdn.static123.com/images/thumbs/900x600/fit/2023/05/13/a66c9d81-52f4-469b-aa42-ff8287925372_1683914543.jpg",
        "https://pt123.cdn.static123.com/images/thumbs/900x600/fit/2023/05/13/cc1a516e-65c0-43c4-aac8-8d9cc533caf7_1683914537.jpg"
      ],
      "header": {
        "title": "Nhà 2MT Góc Ngã 4 khu Tân Tạo Tên Lửa Bình Tân",
        "star": "2",
        "class": {
          "content": "Chuyên mục: Cho thuê nhà Quận Bình Tân",
          "classType": "Cho thuê nhà Quận Bình Tân"
        },
        "address": "Địa chỉ: Đường số 50, Phường Tân Tạo, Quận Bình Tân, Hồ Chí Minh",
        "attributes": {
          "price": "28 triệu/tháng",
          "acreage": "256m2",
          "published": "2 giờ trước",
          "hashtag": "624701"
        }
      },
      "mainContent": {
        "header": "Thông tin mô tả",
        "content": [
          "Cho thuê nhà 2MT GÓC Ngã 4 khu Tân Tạo, Tên Lửa, Bình Tân.",
          "Kết cấu: trệt, 3 lầu, 5 phòng, 5 toilet, vỉa hè 2 bên rộng, đường 2 bên rộng thông thoáng, đối diện có đất trống đậu xe thoải mái.",
          "Nhà phù hợp làm văn phòng công ty, cafe, spa, quán ăn ...",
          "Liên hệ: 0902951674 (Zalo, Imess)."
        ]
      },
      "overview": {
        "header": "Đặc điểm tin đăng",
        "content": [
          { "name": "Mã tin:", "content": "#624701" },
          { "name": "Khu vực", "content": "Cho thuê nhà Hồ Chí Minh" },
          { "name": "Loại tin rao:", "content": "Nhà thuê nguyên căn" },
          { "name": "Đối tượng thuê:", "content": "Tất cả" },
          { "name": "Gói tin:", "content": "Tin VIP 3" },
          { "name": "Ngày đăng:", "content": "Thứ 7, 09:40 13/05/2023" },
          { "name": "Ngày hết hạn:", "content": "Thứ 5, 09:40 18/05/2023" }
        ]
      },
      "contact": {
        "header": "Thông tin liên hệ",
        "content": [
          { "name": "Liên hệ:", "content": "Morning" },
          { "name": "Điện thoại:", "content": "0902951674" },
          { "name": "Zalo", "content": "0902951674" }
        ]
      }
    },
    {
      "images": [
        "https://pt123.cdn.static123.com/images/thumbs/900x600/fit/2023/05/12/z4340180837939-b5f7b5a8f1107489b24c9e367a54c528_1683903034.jpg",
        "https://pt123.cdn.static123.com/images/thumbs/900x600/fit/2023/05/12/z4340184402803-e5358542a6ccbc566f60d9cad2089f29_1683903035.jpg",
        "https://pt123.cdn.static123.com/images/thumbs/900x600/fit/2023/05/12/z4340142187145-a7446ddf4dd21dbb978f4d8e7feef8a9_1683903028.jpg",
        "https://pt123.cdn.static123.com/images/thumbs/900x600/fit/2023/05/12/z4340163282625-1f048625189cfe5fc2bf3414bc15515d_1683903028.jpg",
        "https://pt123.cdn.static123.com/images/thumbs/900x600/fit/2023/05/12/z4340180676672-829635de1c64f8d39465b5861e2913b3_1683903030.jpg",
        "https://pt123.cdn.static123.com/images/thumbs/900x600/fit/2023/05/12/z4340180712858-854edebaae170550b8cd736121382ea8_1683903030.jpg",
        "https://pt123.cdn.static123.com/images/thumbs/900x600/fit/2023/05/12/z4340180737921-907e5e9ae05eee3e6e10f11975d929ee_1683903032.jpg",
        "https://pt123.cdn.static123.com/images/thumbs/900x600/fit/2023/05/12/z4340180763934-3a3e8ce60b4c0acb11249e3ea00fe261_1683903032.jpg",
        "https://pt123.cdn.static123.com/images/thumbs/900x600/fit/2023/05/12/z4340180837939-b5f7b5a8f1107489b24c9e367a54c528_1683903034.jpg"
      ],
      "header": {
        "title": "Chính chủ cho thuê nhà nguyên căn 1 trệt, 2 lầu, sân thượng thoáng mát tại Hương Lộ 2, Bình Tân",
        "star": "2",
        "class": {
          "content": "Chuyên mục: Cho thuê nhà Quận Bình Tân",
          "classType": "Cho thuê nhà Quận Bình Tân"
        },
        "address": "Địa chỉ: Đường Hương lộ 2, Phường Bình Trị Đông A, Quận Bình Tân, Hồ Chí Minh",
        "attributes": {
          "price": "17 triệu/tháng",
          "acreage": "64m2",
          "published": "Hôm nay",
          "hashtag": "624686"
        }
      },
      "mainContent": {
        "header": "Thông tin mô tả",
        "content": [
          "Chính chủ cho thuê nhà nguyên căn tại địa chỉ 704/23/11 Hương Lộ 2, Bình Trị Đông A, Bình Tân.",
          "- DT: 4 x 16m, bao gồm 1 trệt, 2 lầu, Sân thượng trước sau. Nhà thông thoáng, mát mẻ",
          "- Thiết kế hiện đại, tiện nghi với 01 phòng khách, 01 phòng bếp, 04 phòng ngủ có WC riêng, 01 WC chung, sân thượng. Đặc biệt, đã trang bị sẵn máy lạnh cho 2 phòng ngủ.",
          "- Khu an ninh, yên tĩnh, nằm trong hẻm cùng 6m. Camera lắp đặt trước nhà, phòng khách, sân ban công lầu 1 và sân thượng.",
          "- Giá thuê: chỉ 17 triệu/tháng",
          "- Liên hệ: 0947515166 - Đỗ Kiên để đặt lịch xem nhà."
        ]
      },
      "overview": {
        "header": "Đặc điểm tin đăng",
        "content": [
          { "name": "Mã tin:", "content": "#624686" },
          { "name": "Khu vực", "content": "Cho thuê nhà Hồ Chí Minh" },
          { "name": "Loại tin rao:", "content": "Nhà thuê nguyên căn" },
          { "name": "Đối tượng thuê:", "content": "Tất cả" },
          { "name": "Gói tin:", "content": "Tin VIP 3" },
          { "name": "Ngày đăng:", "content": "Thứ 6, 21:51 12/05/2023" },
          { "name": "Ngày hết hạn:", "content": "Chủ Nhật, 21:51 11/06/2023" }
        ]
      },
      "contact": {
        "header": "Thông tin liên hệ",
        "content": [
          { "name": "Liên hệ:", "content": "Kiên" },
          { "name": "Điện thoại:", "content": "0947515166" },
          { "name": "Zalo", "content": "0947515166" }
        ]
      }
    },
    {
      "images": [
        "https://pt123.cdn.static123.com/images/thumbs/900x600/fit/2023/05/09/20230504140026-7d24-wm_1683623885.jpg",
        "https://pt123.cdn.static123.com/images/thumbs/900x600/fit/2023/05/09/20230509094855-9fb0-wm_1683623885.jpg",
        "https://pt123.cdn.static123.com/images/thumbs/900x600/fit/2023/05/09/20230424162856-236c-wm_1683623885.jpg",
        "https://pt123.cdn.static123.com/images/thumbs/900x600/fit/2023/05/09/20230504140026-7d24-wm_1683623885.jpg",
        "https://pt123.cdn.static123.com/images/thumbs/900x600/fit/2023/05/09/20230509094855-9fb0-wm_1683623885.jpg"
      ],
      "header": {
        "title": "Cho thuê nhà nguyên căn MT 143 Đỗ Thị Lời P11 Q3 giáp Q10.",
        "star": "2",
        "class": {
          "content": "Chuyên mục: Cho thuê nhà Quận 3",
          "classType": "Cho thuê nhà Quận 3"
        },
        "address": "Địa chỉ: 143 Đỗ Thị Lời, Phường 11, Quận 3, Hồ Chí Minh",
        "attributes": {
          "price": "28 triệu/tháng",
          "acreage": "30m2",
          "published": "Hôm nay",
          "hashtag": "624328"
        }
      },
      "mainContent": {
        "header": "Thông tin mô tả",
        "content": [
          "Cho thuê nhà nguyên căn MT 143 Đỗ Thị Lời P11 Q3 giáp Q10.",
          "DT: 3.3 x 9 nở hậu 3 8, trệt, lửng, 3 lầu, 4PN 5 Wc.",
          "Có hẻm hông, sử dụng đủ , vị trí đẹp có lề, nhà mới đẹp 100%, tiện ở và kinh doanh hay buôn bán, cty, vp, giáp Q10, đường 10m thông thoáng.",
          "Giá: 28 triệu/tháng.",
          "Tel: 0902501544,0879999930 A. Cơ 24/7"
        ]
      },
      "overview": {
        "header": "Đặc điểm tin đăng",
        "content": [
          { "name": "Mã tin:", "content": "#624328" },
          { "name": "Khu vực", "content": "Cho thuê nhà Hồ Chí Minh" },
          { "name": "Loại tin rao:", "content": "Nhà thuê nguyên căn" },
          { "name": "Đối tượng thuê:", "content": "Tất cả" },
          { "name": "Gói tin:", "content": "Tin VIP 3" },
          { "name": "Ngày đăng:", "content": "Thứ 4, 07:24 10/05/2023" },
          { "name": "Ngày hết hạn:", "content": "Chủ Nhật, 16:18 14/05/2023" }
        ]
      },
      "contact": {
        "header": "Thông tin liên hệ",
        "content": [
          { "name": "Liên hệ:", "content": "hungthiennguyen" },
          { "name": "Điện thoại:", "content": "0902501544" },
          { "name": "Zalo", "content": "0902501544" }
        ]
      }
    },
    {
      "images": [
        "https://pt123.cdn.static123.com/images/thumbs/900x600/fit/2023/04/16/z4269248590720-32414626433177dcbe01471e80fb6106_1681632734.jpg",
        "https://pt123.cdn.static123.com/images/thumbs/900x600/fit/2022/04/06/hhhh_1649240358.jpg",
        "https://pt123.cdn.static123.com/images/thumbs/900x600/fit/2022/04/06/h2_1649240419.jpg",
        "https://pt123.cdn.static123.com/images/thumbs/900x600/fit/2022/04/06/h1_1649240357.jpg",
        "https://pt123.cdn.static123.com/images/thumbs/900x600/fit/2023/04/16/z4269248538942-1fedb879ae3b20c775576a741d3ea244_1681632733.jpg",
        "https://pt123.cdn.static123.com/images/thumbs/900x600/fit/2023/04/16/z4269248527701-0a96913e168308dc94fea937f5b203d1_1681632734.jpg",
        "https://pt123.cdn.static123.com/images/thumbs/900x600/fit/2023/04/16/z4269248518394-9ae8020a06a300b50c8cac966cebe414_1681632734.jpg",
        "https://pt123.cdn.static123.com/images/thumbs/900x600/fit/2023/04/16/z4269248526727-1c45a93a30000c0f14b02338f558bc53_1681632735.jpg",
        "https://pt123.cdn.static123.com/images/thumbs/900x600/fit/2023/04/16/z4269248520281-ac10a92332ab2be226eae0c0836cd697_1681632735.jpg",
        "https://pt123.cdn.static123.com/images/thumbs/900x600/fit/2023/04/16/z4269248519831-2f227b1891e9d930d52a9f582913f7ae_1681632736.jpg",
        "https://pt123.cdn.static123.com/images/thumbs/900x600/fit/2023/04/16/z4269248529019-51649203e62ee42b05c216e264f1a48e_1681632736.jpg",
        "https://pt123.cdn.static123.com/images/thumbs/900x600/fit/2022/04/06/h_1649240358.jpg",
        "https://pt123.cdn.static123.com/images/thumbs/900x600/fit/2022/04/06/hy_1649240385.jpg",
        "https://pt123.cdn.static123.com/images/thumbs/900x600/fit/2023/04/16/z4269248590720-32414626433177dcbe01471e80fb6106_1681632734.jpg",
        "https://pt123.cdn.static123.com/images/thumbs/900x600/fit/2022/04/06/hhhh_1649240358.jpg"
      ],
      "header": {
        "title": "Cho thuê nhà nguyên căn diện tích 500m2; giá thuê 20 Triệu có thương lượng, tại P, An Hải Bắc, Quận Sơn Trà, Đà Nẵng",
        "star": "2",
        "class": {
          "content": "Chuyên mục: Cho thuê nhà Quận Sơn Trà",
          "classType": "Cho thuê nhà Quận Sơn Trà"
        },
        "address": "Địa chỉ: 648 Ngô Quyền, Phường An Hải Bắc, Quận Sơn Trà, Đà Nẵng",
        "attributes": {
          "price": "20 triệu/tháng",
          "acreage": "500m2",
          "published": "Hôm nay",
          "hashtag": "598699"
        }
      },
      "mainContent": {
        "header": "Thông tin mô tả",
        "content": [
          "Cho thuê nhà nguyên căn tại 648 Ngô Quyền, Phường An Hải Bắc, Quận Sơn Trà, Đà Nẵng",
          "Diện tích sử dụng: 500m2 - Diện tích đất: 125m2. Đường 60m",
          "Kết cấu: 4 Tầng, 10 Phòng ngủ, 1 phòng khách lớn 60m2, 2 bếp, 8 Wc, 2 sân thượng Trước và Sau",
          "+ Tầng 1 ( 125m2): có 1 bếp lớn, 1 phòng ngủ, 2 nhà vệ sinh",
          "+ Tầng 2: ( 125m2) Trước có 2 phòng ngủ và 2 nhà vệ sinh riêng từng phòng; Sau có 2 phòng ngủ chung 1 nhà vệ sinh.",
          "+ Tầng 3 ( 125m2): Trước 2 phòng ngủ chung 1 nhà vệ sinh; Sau 1 phòng ngủ, 1 nhà vệ sinh",
          "+ Tầng 4 (125m2): Trước có 2 phòng ngủ, chung nhà vệ sinh. Tầng 4 có bếp",
          "Tất cả các phòng đều đầy đủ tiện nghi",
          "Nhà sạch sẽ. thoáng mát.",
          "Sát bên trường Đại Học, Gần Chợ, khu công nghiệp An Đồn, gần cầu sông Hàn, ",
          "Thuê có thể kinh doanh mọi ngành nghề: Kinh doanh buôn bán, Spa, mở công ty, Hommestay, Khách sạn  mini, ",
          "Gia thuê: 20 triệu ( có thượng) cho khách thiện chí. Hợp đồng thuê ít nhất 2 nam",
          "Liên hệ chính chủ nhà để trao đổi và thương lượng và xem nhà: 0905761005"
        ]
      },
      "overview": {
        "header": "Đặc điểm tin đăng",
        "content": [
          { "name": "Mã tin:", "content": "#598699" },
          { "name": "Khu vực", "content": "Cho thuê nhà Đà Nẵng" },
          { "name": "Loại tin rao:", "content": "Nhà thuê nguyên căn" },
          { "name": "Đối tượng thuê:", "content": "Tất cả" },
          { "name": "Gói tin:", "content": "Tin VIP 3" },
          { "name": "Ngày đăng:", "content": "Chủ Nhật, 15:38 16/04/2023" },
          { "name": "Ngày hết hạn:", "content": "Thứ 3, 15:38 16/05/2023" }
        ]
      },
      "contact": {
        "header": "Thông tin liên hệ",
        "content": [
          { "name": "Liên hệ:", "content": "Chú Nhâm" },
          { "name": "Điện thoại:", "content": "0905761005" },
          { "name": "Zalo", "content": "0905761005" }
        ]
      }
    },
    {
      "images": [
        "https://pt123.cdn.static123.com/images/thumbs/900x600/fit/2023/05/13/z4335977523126-24ec57965b8ef06201efc66c3ddc3b02_1683949378.jpg",
        "https://pt123.cdn.static123.com/images/thumbs/900x600/fit/2023/05/13/z4335977352317-26ba2ab5ba14df1c933b2ddc970944ec_1683949375.jpg",
        "https://pt123.cdn.static123.com/images/thumbs/900x600/fit/2023/05/13/z4335977449072-4d167ec95633a41faedf8c2306430525_1683949376.jpg",
        "https://pt123.cdn.static123.com/images/thumbs/900x600/fit/2023/05/13/z4335977489498-6d8b52f73e934a731c535718e80eb045_1683949377.jpg",
        "https://pt123.cdn.static123.com/images/thumbs/900x600/fit/2023/05/13/z4335977503720-26bf0ba2622c858ccb6f60a8481b9f0a_1683949377.jpg",
        "https://pt123.cdn.static123.com/images/thumbs/900x600/fit/2023/05/13/z4335977523126-24ec57965b8ef06201efc66c3ddc3b02_1683949378.jpg",
        "https://pt123.cdn.static123.com/images/thumbs/900x600/fit/2023/05/13/z4335977352317-26ba2ab5ba14df1c933b2ddc970944ec_1683949375.jpg"
      ],
      "header": {
        "title": "Cho thuê CHCC Virgo . Trung tâm TP Nha Trang. Cách quảng trường 2/4 và biển chỉ 250m,",
        "class": {
          "content": "Chuyên mục: Cho thuê nhà Thành Phố Nha Trang",
          "classType": "Cho thuê nhà Thành Phố Nha Trang"
        },
        "address": "Địa chỉ: Đường Nguyễn Thị Minh Khai, Lộc Thọ, Nha Trang, Khánh Hòa",
        "attributes": {
          "price": "12 triệu/tháng",
          "acreage": "60m2",
          "published": "1 giờ trước",
          "hashtag": "624729"
        }
      },
      "mainContent": {
        "header": "Thông tin mô tả",
        "content": [
          "Cho thuê CHCC Virgo . Trung tâm TP Nha Trang. Vị trí: 39 - 41 Nguyễn Thị Minh Khai. Phường tân lập- Nha Trang.Cách quảng trường 2/4 và biển chỉ 250m,Cách khu phố Tây và chợ đêm 100m.  Xung quanh là cụm khách sạn sầm uất..Đầy đủ tiện ích phòng gym,hồ bơi vô cực.Full nội thất cao cấp xịn xò. ——————-Diện tích : 60m2 ( 2 phòng ngủ, 2 wc ) Gồm : 2 phòng ngủ, 2 WC Giá 12 triệu/ tháng.",
          "Liên hệ Chuyên nhận ký gửi cho thuê căn hộ cao cấp tại TP Nha Trang: GoldCoast, Virgo, Hud Building. Panorama."
        ]
      },
      "overview": {
        "header": "Đặc điểm tin đăng",
        "content": [
          { "name": "Mã tin:", "content": "#624729" },
          { "name": "Khu vực", "content": "Cho thuê nhà Khánh Hòa" },
          { "name": "Loại tin rao:", "content": "Nhà thuê nguyên căn" },
          { "name": "Đối tượng thuê:", "content": "Tất cả" },
          { "name": "Gói tin:", "content": "Tin thường" },
          { "name": "Ngày đăng:", "content": "Thứ 7, 11:02 13/05/2023" },
          { "name": "Ngày hết hạn:", "content": "Thứ 5, 11:02 18/05/2023" }
        ]
      },
      "contact": {
        "header": "Thông tin liên hệ",
        "content": [
          { "name": "Liên hệ:", "content": "thanh trường" },
          { "name": "Điện thoại:", "content": "0326482819" },
          { "name": "Zalo", "content": "0326482819" }
        ]
      }
    },
    {
      "images": [
        "https://pt123.cdn.static123.com/images/thumbs/900x600/fit/2023/05/13/z4335044533403-12bf7fc4e2206febefbcc89c3fa15bbb_1683948088.jpg",
        "https://pt123.cdn.static123.com/images/thumbs/900x600/fit/2023/05/13/z4335044502993-b0000731beb1b425c84b2b5a82c9c8c6_1683948087.jpg",
        "https://pt123.cdn.static123.com/images/thumbs/900x600/fit/2023/05/13/z4335044509958-341c36e6a5dcffb2b2d4a2cfb50954a1_1683948087.jpg",
        "https://pt123.cdn.static123.com/images/thumbs/900x600/fit/2023/05/13/z4335044518009-b75f6dc8a553872ddf3eb51ce0f177d0_1683948087.jpg",
        "https://pt123.cdn.static123.com/images/thumbs/900x600/fit/2023/05/13/z4335044522247-ac84869c5a28eb8d98de8099cc232160_1683948087.jpg",
        "https://pt123.cdn.static123.com/images/thumbs/900x600/fit/2023/05/13/z4335044533403-12bf7fc4e2206febefbcc89c3fa15bbb_1683948088.jpg",
        "https://pt123.cdn.static123.com/images/thumbs/900x600/fit/2023/05/13/z4335044502993-b0000731beb1b425c84b2b5a82c9c8c6_1683948087.jpg"
      ],
      "header": {
        "title": "Cho Thuê CH 3 Phòng Ngủ CT3 Vĩnh Điềm Trung View sông Nha Trang",
        "class": {
          "content": "Chuyên mục: Cho thuê nhà Thành Phố Nha Trang",
          "classType": "Cho thuê nhà Thành Phố Nha Trang"
        },
        "address": "Địa chỉ: Đường 19/5, Vĩnh Hiệp, Nha Trang, Khánh Hòa",
        "attributes": {
          "price": "12 triệu/tháng",
          "acreage": "99m2",
          "published": "1 giờ trước",
          "hashtag": "624728"
        }
      },
      "mainContent": {
        "header": "Thông tin mô tả",
        "content": [
          "Cho Thuê CH 3 Phòng Ngủ CT3. Vĩnh Điềm Trung. Đủ nội thất xịn xò, Nằm trong khu đô thị VĐT với đầy đủ tiện ích, trường học, bệnh viện quốc tế, khu nhà hàng, ăn uống cà phê sầm uất.",
          "Diện tích: 99m² ( 3 PN, 2 WC ) View sông. Giá Thuê : 11 triệu/ tháng Điện nước tính theo đơn giá nhà nước",
          "Nhận ký gửi Mua Bán Cho Thuê Căn Hộ"
        ]
      },
      "overview": {
        "header": "Đặc điểm tin đăng",
        "content": [
          { "name": "Mã tin:", "content": "#624728" },
          { "name": "Khu vực", "content": "Cho thuê nhà Khánh Hòa" },
          { "name": "Loại tin rao:", "content": "Nhà thuê nguyên căn" },
          { "name": "Đối tượng thuê:", "content": "Tất cả" },
          { "name": "Gói tin:", "content": "Tin thường" },
          { "name": "Ngày đăng:", "content": "Thứ 7, 11:02 13/05/2023" },
          { "name": "Ngày hết hạn:", "content": "Thứ 5, 11:02 18/05/2023" }
        ]
      },
      "contact": {
        "header": "Thông tin liên hệ",
        "content": [
          { "name": "Liên hệ:", "content": "thanh trường" },
          { "name": "Điện thoại:", "content": "0326482819" },
          { "name": "Zalo", "content": "0326482819" }
        ]
      }
    },
    {
      "images": [
        "https://pt123.cdn.static123.com/images/thumbs/900x600/fit/2023/05/13/z4335032506066-2954512a8004a35f54cd43c7d32f8050_1683947569.jpg",
        "https://pt123.cdn.static123.com/images/thumbs/900x600/fit/2023/05/13/z4335032487969-fd9414e44c2f5ec3067433bd3f940c00_1683947565.jpg",
        "https://pt123.cdn.static123.com/images/thumbs/900x600/fit/2023/05/13/z4335032493107-ea2a1c389747b834cb278128294788dc_1683947566.jpg",
        "https://pt123.cdn.static123.com/images/thumbs/900x600/fit/2023/05/13/z4335032498689-57537bf7a9cc9840e5c2502dae533c6f_1683947567.jpg",
        "https://pt123.cdn.static123.com/images/thumbs/900x600/fit/2023/05/13/z4335032499812-a860a058a0a375ff6b100cbdfa182d36_1683947568.jpg",
        "https://pt123.cdn.static123.com/images/thumbs/900x600/fit/2023/05/13/z4335032506066-2954512a8004a35f54cd43c7d32f8050_1683947569.jpg",
        "https://pt123.cdn.static123.com/images/thumbs/900x600/fit/2023/05/13/z4335032487969-fd9414e44c2f5ec3067433bd3f940c00_1683947565.jpg"
      ],
      "header": {
        "title": "Cho Thuê CHCC Toà Nam Goldcoast. Trung Tâm Tp Nha Trang. Cách Biển 50m.",
        "class": {
          "content": "Chuyên mục: Cho thuê nhà Thành Phố Nha Trang",
          "classType": "Cho thuê nhà Thành Phố Nha Trang"
        },
        "address": "Địa chỉ: Đường Trần Hưng Đạo, Lộc Thọ, Nha Trang, Khánh Hòa",
        "attributes": {
          "price": "12 triệu/tháng",
          "acreage": "56m2",
          "published": "1 giờ trước",
          "hashtag": "624723"
        }
      },
      "mainContent": {
        "header": "Thông tin mô tả",
        "content": [
          "Cho Thuê CHCC Toà Nam Goldcoast. Trung Tâm Tp Nha Trang. Cách Biển 50m. Tầng Cao. Đủ nội thất . View: xéo biển và đường Lý Tự TrọngBên dưới là trung tâm thương mại,siêu thị,cà phê...Diện Tích : 56m2Giá : 12 triệu/ tháng——————Liên hệ Chi: Chuyên nhận ký gửi cho thuê căn hộ cao cấp tại TP Nha Trang: GoldCoast, Virgo, Hud Building. Panorama."
        ]
      },
      "overview": {
        "header": "Đặc điểm tin đăng",
        "content": [
          { "name": "Mã tin:", "content": "#624723" },
          { "name": "Khu vực", "content": "Cho thuê nhà Khánh Hòa" },
          { "name": "Loại tin rao:", "content": "Nhà thuê nguyên căn" },
          { "name": "Đối tượng thuê:", "content": "Tất cả" },
          { "name": "Gói tin:", "content": "Tin thường" },
          { "name": "Ngày đăng:", "content": "Thứ 7, 11:02 13/05/2023" },
          { "name": "Ngày hết hạn:", "content": "Thứ 5, 11:02 18/05/2023" }
        ]
      },
      "contact": {
        "header": "Thông tin liên hệ",
        "content": [
          { "name": "Liên hệ:", "content": "thanh trường" },
          { "name": "Điện thoại:", "content": "0326482819" },
          { "name": "Zalo", "content": "0326482819" }
        ]
      }
    },
    {
      "images": [
        "https://pt123.cdn.static123.com/images/thumbs/900x600/fit/2023/04/28/z3495868923826-9f1252fac5b8d378b76c2808128cf10d_1682635715.jpg",
        "https://pt123.cdn.static123.com/images/thumbs/900x600/fit/2019/07/01/62245483-348150315903623-3919948459863441408-n_1561972015.jpg",
        "https://pt123.cdn.static123.com/images/thumbs/900x600/fit/2019/07/01/62604037-829105350815941-496951368532099072-n_1561972025.jpg",
        "https://pt123.cdn.static123.com/images/thumbs/900x600/fit/2023/04/28/z3495868909867-1c64f8eae0881e4a14bba14ad245d46a_1682635714.jpg",
        "https://pt123.cdn.static123.com/images/thumbs/900x600/fit/2023/04/28/z3495868924913-9d9220d67fe43d958874586253f7262f_1682635714.jpg",
        "https://pt123.cdn.static123.com/images/thumbs/900x600/fit/2023/04/28/z3495868923826-9f1252fac5b8d378b76c2808128cf10d_1682635715.jpg",
        "https://pt123.cdn.static123.com/images/thumbs/900x600/fit/2019/07/01/62245483-348150315903623-3919948459863441408-n_1561972015.jpg"
      ],
      "header": {
        "title": "NHÀ NGUYÊN CĂN CHO THUÊ TIỆN MỞ VĂN PHÒNG HOẶC ĐỂ Ở HXH 8M 269/45 PHAN HUY ÍCH, P.14, Q.GÒ VẤP, 1 TRỆT, DT: 4X14M, 2PN",
        "class": {
          "content": "Chuyên mục: Cho thuê nhà Quận Gò Vấp",
          "classType": "Cho thuê nhà Quận Gò Vấp"
        },
        "address": "Địa chỉ: 269/45 Đường Phan Huy Ích, Phường 14, Quận Gò Vấp, Hồ Chí Minh",
        "attributes": {
          "price": "6.9 triệu/tháng",
          "acreage": "60m2",
          "published": "1 giờ trước",
          "hashtag": "284343"
        }
      },
      "mainContent": {
        "header": "Thông tin mô tả",
        "content": [
          "Nhà nguyên căn cho thuê hẻm 1 trục xe tải 8m, hẻm hai xe hơi tránh nhau cách Phan Huy Ích 50m, thiết kế đẹp hoàn hảo.",
          "- Diện Tích: 4 x 14m, Gồm: 1 trệt",
          "+ Dưới tầng trệt gồm 2 phòng rất rộng (60m2) thiết kế mới hoàn toàn, rất đẹp tiện mở văn phòng giao dịnh, kinh doanh online hoặc ở …",
          "+ Phòng ngủ rộng thiết kế rất đẹp mới hoàn toàn, WC riêng",
          "+ Thiết kế sang trọng, hiện đại, cửa, cầu thang gỗ và đá hoa cương rất đẹp.",
          "+ Khu dân cư an ninh, đông đúc, hẻm rộng 8m ô tô ra vào thoải mái.",
          "+ Rất tiện lợi để mở văn phòng công ty, gia đình ở hay kinh doanh mọi ngành nghề",
          "Địa chỉ: 269/45 Phan Huy Ích, Phường 14, Quận Gò Vấp, TP. HCM.",
          "Giá giảm sâu chỉ: 6.9 triệu/tháng (hình ảnh thật).",
          "LH: 0937554570 A. Hoàng.",
          "Tìm kiếm theo từ khóa: Cho thuê nhà phường 14 quận Gò Vấp , Cho thuê nhà đường Phan Huy Ích , Cho thuê nhà đường Phan Huy Ích quận Gò Vấp , Cho thuê nhà phường 14 , Cho thuê nhà đường Phan Huy Ích phường 14, Cho thuê nhà quận Gò Vấp, Nhà cho thuê Quận Gò Vấp, cho thue nha quan go vap, Văn phòng cho thuê quận gò vấp, nhà cho thuê làm văn phòng, Van phong cho thue Go Vap."
        ]
      },
      "overview": {
        "header": "Đặc điểm tin đăng",
        "content": [
          { "name": "Mã tin:", "content": "#284343" },
          { "name": "Khu vực", "content": "Cho thuê nhà Hồ Chí Minh" },
          { "name": "Loại tin rao:", "content": "Nhà thuê nguyên căn" },
          { "name": "Đối tượng thuê:", "content": "Tất cả" },
          { "name": "Gói tin:", "content": "Tin thường" },
          { "name": "Ngày đăng:", "content": "Thứ 7, 10:28 13/05/2023" },
          { "name": "Ngày hết hạn:", "content": "Thứ 5, 16:23 18/05/2023" }
        ]
      },
      "contact": {
        "header": "Thông tin liên hệ",
        "content": [
          { "name": "Liên hệ:", "content": "hoangle2706" },
          { "name": "Điện thoại:", "content": "0937554570" },
          { "name": "Zalo", "content": "0937554570" }
        ]
      }
    },
    {
      "images": [
        "https://pt123.cdn.static123.com/images/thumbs/900x600/fit/2023/05/13/29a1e6721032ce6c9723_1683946383.jpg",
        "https://pt123.cdn.static123.com/images/thumbs/900x600/fit/2023/05/13/ccfb19b6eef630a869e7_1683946390.jpg",
        "https://pt123.cdn.static123.com/images/thumbs/900x600/fit/2023/05/13/bc2afa700d30d36e8a21_1683946389.jpg",
        "https://pt123.cdn.static123.com/images/thumbs/900x600/fit/2023/05/13/0d0185047244ac1af555_1683946386.jpg",
        "https://pt123.cdn.static123.com/images/thumbs/900x600/fit/2023/05/13/17328d0a7a4aa414fd5b_1683946388.jpg",
        "https://pt123.cdn.static123.com/images/thumbs/900x600/fit/2023/05/13/2647888d7ecda093f9dc_1683946383.jpg",
        "https://pt123.cdn.static123.com/images/thumbs/900x600/fit/2023/05/13/d60516ffe0bf3ee167ae_1683946386.jpg",
        "https://pt123.cdn.static123.com/images/thumbs/900x600/fit/2023/05/13/29a1e6721032ce6c9723_1683946383.jpg",
        "https://pt123.cdn.static123.com/images/thumbs/900x600/fit/2023/05/13/ccfb19b6eef630a869e7_1683946390.jpg"
      ],
      "header": {
        "title": "NHÀ NGUYÊN CĂN 40M2 GÁC LỬNG 2M NGAY CHỢ GÒ VẤP, IUH",
        "class": {
          "content": "Chuyên mục: Cho thuê nhà Quận Gò Vấp",
          "classType": "Cho thuê nhà Quận Gò Vấp"
        },
        "address": "Địa chỉ: Đường Dương Quảng Hàm, Phường 5, Quận Gò Vấp, Hồ Chí Minh",
        "attributes": {
          "price": "5 triệu/tháng",
          "acreage": "40m2",
          "published": "2 giờ trước",
          "hashtag": "624677"
        }
      },
      "mainContent": {
        "header": "Thông tin mô tả",
        "content": [
          "Nhà thoáng đẹp cho thuê tại Nguyễn Thái Sơn, P5, Gò Vấp (gần đoạn ngã tư Dương Quảng Hàm và Nguyễn Thái Sơn.",
          "Chỉ 5 tr /tháng.",
          "Hẻm rộng thuận tiện cho các phương tiện (ô tô, xe máy.. ).",
          "An ninh nơi đây trên cả tuyệt.",
          "Cửa sử dụng vân tay, giờ giấc tự do.",
          "Nơi để xe rộng rãi.",
          "️ Phòng có máy lạnh, nước nóng năng lượng mặt trời, cửa sổ thoáng mát.",
          "️ Kệ bếp nấu ăn",
          "Nhà vệ sinh riêng, mọi thiết bị đều được trang bị hiện đại.",
          "Hiện nay việc tìm một chỗ ở thuận tiện cho việc đi lại phục vụ cho công việc đó là nỗi ám ảnh biết bao nhiêu người nhưng giờ đây bạn khỏi lo vì đã có tôi:",
          "Dương Quảng Hàm đi đến công viên Gia Định, Cạnh bên trường ĐH Công Nghiệp, nhà thờ Bến Cát, công viên Gò Vấp, đường đến sân bay, ga tàu, bến xe rất gần,...",
          "Để tận hưởng với căn phòng trên cả tuyệt vời này hãy liên hệ với Miss Loan để được xem phòng miễn phí nhé"
        ]
      },
      "overview": {
        "header": "Đặc điểm tin đăng",
        "content": [
          { "name": "Mã tin:", "content": "#624677" },
          { "name": "Khu vực", "content": "Cho thuê nhà Hồ Chí Minh" },
          { "name": "Loại tin rao:", "content": "Nhà thuê nguyên căn" },
          { "name": "Đối tượng thuê:", "content": "Tất cả" },
          { "name": "Gói tin:", "content": "Tin thường" },
          { "name": "Ngày đăng:", "content": "Thứ 7, 09:59 13/05/2023" },
          { "name": "Ngày hết hạn:", "content": "Thứ 4, 16:47 17/05/2023" }
        ]
      },
      "contact": {
        "header": "Thông tin liên hệ",
        "content": [
          { "name": "Liên hệ:", "content": "Loan Nguyễn" },
          { "name": "Điện thoại:", "content": "0967726409" },
          { "name": "Zalo", "content": "0967726409" },
          { "name": "Facebook", "content": "Loan Yumi" }
        ]
      }
    },
    {
      "images": [
        "https://pt123.cdn.static123.com/images/thumbs/900x600/fit/2023/05/12/den-lu-16_1683903225.jpg",
        "https://pt123.cdn.static123.com/images/thumbs/900x600/fit/2023/05/12/den-lu-11_1683903207.jpg",
        "https://pt123.cdn.static123.com/images/thumbs/900x600/fit/2023/05/12/den-lu-12_1683903211.jpg",
        "https://pt123.cdn.static123.com/images/thumbs/900x600/fit/2023/05/12/den-lu-13_1683903215.jpg",
        "https://pt123.cdn.static123.com/images/thumbs/900x600/fit/2023/05/12/den-lu-14_1683903217.jpg",
        "https://pt123.cdn.static123.com/images/thumbs/900x600/fit/2023/05/12/den-lu-15_1683903220.jpg",
        "https://pt123.cdn.static123.com/images/thumbs/900x600/fit/2023/05/12/den-lu-16_1683903225.jpg",
        "https://pt123.cdn.static123.com/images/thumbs/900x600/fit/2023/05/12/den-lu-11_1683903207.jpg"
      ],
      "header": {
        "title": "Cho thuê nhà Đền Lừ 1 năm 2023 50m2 x 3.5",
        "class": {
          "content": "Chuyên mục: Cho thuê nhà Quận Hoàng Mai",
          "classType": "Cho thuê nhà Quận Hoàng Mai"
        },
        "address": "Địa chỉ: Lô 3 Đường Đền Lừ, Phường Hoàng Văn Thụ, Quận Hoàng Mai, Hà Nội",
        "attributes": {
          "price": "15 triệu/tháng",
          "acreage": "50m2",
          "published": "14 giờ trước",
          "hashtag": "617142"
        }
      },
      "mainContent": {
        "header": "Thông tin mô tả",
        "content": [
          "Chính chủ cho thuê nhà tại phân lô Đền Lừ 1. Nhà 3 tầng và tum, tầng 1 nguyên mặt sàn, tầng 2 và 3 chia 2 phòng ngủ mỗi tầng, tầng 4 tum và sân phơi. Mặt tiền 5m, đường trước nhà đỗ được cả xe container, vỉa hè rộng 2,5m. Vị trí thuận lợi làm văn phòng, kinh doanh, kho hàng. Bên thuê được phép sửa nhà tùy ý. Nội thất có điều hòa, nóng lạnh đầy đủ. Thời hạn thuê kéo dài."
        ]
      },
      "overview": {
        "header": "Đặc điểm tin đăng",
        "content": [
          { "name": "Mã tin:", "content": "#617142" },
          { "name": "Khu vực", "content": "Cho thuê nhà Hà Nội" },
          { "name": "Loại tin rao:", "content": "Nhà thuê nguyên căn" },
          { "name": "Đối tượng thuê:", "content": "Tất cả" },
          { "name": "Gói tin:", "content": "Tin thường" },
          { "name": "Ngày đăng:", "content": "Thứ 6, 21:54 12/05/2023" },
          { "name": "Ngày hết hạn:", "content": "Thứ 2, 21:54 22/05/2023" }
        ]
      },
      "contact": {
        "header": "Thông tin liên hệ",
        "content": [
          { "name": "Liên hệ:", "content": "Duong Hai Nam" },
          { "name": "Điện thoại:", "content": "0983918927" },
          { "name": "Zalo", "content": "0983918927" }
        ]
      }
    },
    {
      "images": [
        "https://pt123.cdn.static123.com/images/thumbs/900x600/fit/2023/05/12/344544522-757080695890747-6097671538247550846-n_1683895877.jpg",
        "https://pt123.cdn.static123.com/images/thumbs/900x600/fit/2023/05/12/344524837-743213484043802-3843998966025213936-n_1683895872.jpg",
        "https://pt123.cdn.static123.com/images/thumbs/900x600/fit/2023/05/12/344499847-277446891405528-6328509952213530249-n_1683895872.jpg",
        "https://pt123.cdn.static123.com/images/thumbs/900x600/fit/2023/05/12/344517182-1874954122877589-1121356747747791324-n_1683895873.jpg",
        "https://pt123.cdn.static123.com/images/thumbs/900x600/fit/2023/05/12/344517195-280803440948093-5437995649768375628-n_1683895873.jpg",
        "https://pt123.cdn.static123.com/images/thumbs/900x600/fit/2023/05/12/344517180-743102074164563-5721819834421731460-n_1683895874.jpg",
        "https://pt123.cdn.static123.com/images/thumbs/900x600/fit/2023/05/12/344553297-1291405568253712-7770930412123998654-n_1683895875.jpg",
        "https://pt123.cdn.static123.com/images/thumbs/900x600/fit/2023/05/12/344534654-767357328302819-4318324348001882024-n_1683895876.jpg",
        "https://pt123.cdn.static123.com/images/thumbs/900x600/fit/2023/05/12/344533791-164570979907961-2743073328876781857-n_1683895876.jpg",
        "https://pt123.cdn.static123.com/images/thumbs/900x600/fit/2023/05/12/344534655-1436626177147406-6936089516082786104-n_1683895877.jpg",
        "https://pt123.cdn.static123.com/images/thumbs/900x600/fit/2023/05/12/344544522-757080695890747-6097671538247550846-n_1683895877.jpg",
        "https://pt123.cdn.static123.com/images/thumbs/900x600/fit/2023/05/12/344524837-743213484043802-3843998966025213936-n_1683895872.jpg"
      ],
      "header": {
        "title": "cho thuê nhà nguyên căn số 41/3 đội cung",
        "class": {
          "content": "Chuyên mục: Cho thuê nhà Quận 11",
          "classType": "Cho thuê nhà Quận 11"
        },
        "address": "Địa chỉ: 41/3 Đường Đội Cung, Phường 11, Quận 11, Hồ Chí Minh",
        "attributes": {
          "price": "12 triệu/tháng",
          "acreage": "38m2",
          "published": "16 giờ trước",
          "hashtag": "624684"
        }
      },
      "mainContent": {
        "header": "Thông tin mô tả",
        "content": [
          "nhà diện tích 38m2 , ngang 4,2m dài 9m , 2 lầu 1 trệt , 3 phòng ngủ 3 wc giá có thể thương lượng",
          "giá có thể thương lượng"
        ]
      },
      "overview": {
        "header": "Đặc điểm tin đăng",
        "content": [
          { "name": "Mã tin:", "content": "#624684" },
          { "name": "Khu vực", "content": "Cho thuê nhà Hồ Chí Minh" },
          { "name": "Loại tin rao:", "content": "Nhà thuê nguyên căn" },
          { "name": "Đối tượng thuê:", "content": "Tất cả" },
          { "name": "Gói tin:", "content": "Tin miễn phí" },
          { "name": "Ngày đăng:", "content": "Thứ 6, 19:51 12/05/2023" },
          { "name": "Ngày hết hạn:", "content": "Thứ 4, 19:51 17/05/2023" }
        ]
      },
      "contact": {
        "header": "Thông tin liên hệ",
        "content": [
          { "name": "Liên hệ:", "content": "lương gia kiến vũ" },
          { "name": "Điện thoại:", "content": "0708997801" },
          { "name": "Zalo", "content": "0708997801" }
        ]
      }
    },
    {
      "images": [
        "https://pt123.cdn.static123.com/images/thumbs/900x600/fit/2023/02/25/img-1676283708452-1676604080951_1677313659.jpg",
        "https://pt123.cdn.static123.com/images/thumbs/900x600/fit/2023/02/25/screenshot-2023-02-17-17-15-34-18-cd9f342f505fc08af23d5639700d5c03_1677313656.jpg",
        "https://pt123.cdn.static123.com/images/thumbs/900x600/fit/2023/02/25/img-1676283709200-1676604083068_1677313655.jpg",
        "https://pt123.cdn.static123.com/images/thumbs/900x600/fit/2023/02/25/img-1676283709070-1676604082490_1677313656.jpg",
        "https://pt123.cdn.static123.com/images/thumbs/900x600/fit/2023/02/25/img-1676283708969-1676604082090_1677313657.jpg",
        "https://pt123.cdn.static123.com/images/thumbs/900x600/fit/2023/02/25/img-1676283708861-1676604081893_1677313657.jpg",
        "https://pt123.cdn.static123.com/images/thumbs/900x600/fit/2023/02/25/img-1676283708743-1676604081713_1677313658.jpg",
        "https://pt123.cdn.static123.com/images/thumbs/900x600/fit/2023/02/25/img-1676283708617-1676604081265_1677313658.jpg",
        "https://pt123.cdn.static123.com/images/thumbs/900x600/fit/2023/02/25/img-1676283708346-1676604080458_1677313659.jpg",
        "https://pt123.cdn.static123.com/images/thumbs/900x600/fit/2023/02/25/img-1676283708452-1676604080951_1677313659.jpg",
        "https://pt123.cdn.static123.com/images/thumbs/900x600/fit/2023/02/25/screenshot-2023-02-17-17-15-34-18-cd9f342f505fc08af23d5639700d5c03_1677313656.jpg"
      ],
      "header": {
        "title": "Cho thuê nhà 1 trệt 1lầu 2 phòng ngủ. 4/11/7 Đường lưu chí hiếu phường Tây thạnh quận Tân Phú",
        "class": {
          "content": "Chuyên mục: Cho thuê nhà Quận Tân Phú",
          "classType": "Cho thuê nhà Quận Tân Phú"
        },
        "address": "Địa chỉ: Đường Lưu Chí Hiếu, Phường Tây Thạnh, Quận Tân Phú, Hồ Chí Minh",
        "attributes": {
          "price": "7 triệu/tháng",
          "acreage": "60m2",
          "published": "17 giờ trước",
          "hashtag": "617286"
        }
      },
      "mainContent": {
        "header": "Thông tin mô tả",
        "content": [
          "Cho thuê nguyên căn nhà hẻm 4/11/7 đường lưu chí hiếu, phường Tây thạnh ,quận Tân Phú",
          "Diện tích 3,1m x 10m . 1 trệt 1 lầu . Có 2 phòng ngủ 2 toilet trên dưới.",
          "Vị trí gần trường học cấp 1, 2, 3 tây thạnh. Phía sau ngân hàng Vietcombank.",
          "Giá cho thuê 7 triệu 1 tháng. Cọc trước 1 tháng."
        ]
      },
      "overview": {
        "header": "Đặc điểm tin đăng",
        "content": [
          { "name": "Mã tin:", "content": "#617286" },
          { "name": "Khu vực", "content": "Cho thuê nhà Hồ Chí Minh" },
          { "name": "Loại tin rao:", "content": "Nhà thuê nguyên căn" },
          { "name": "Đối tượng thuê:", "content": "Tất cả" },
          { "name": "Gói tin:", "content": "Tin thường" },
          { "name": "Ngày đăng:", "content": "Thứ 6, 18:32 12/05/2023" },
          { "name": "Ngày hết hạn:", "content": "Thứ 4, 18:32 17/05/2023" }
        ]
      },
      "contact": {
        "header": "Thông tin liên hệ",
        "content": [
          { "name": "Liên hệ:", "content": "loit3574@gmail.com" },
          { "name": "Điện thoại:", "content": "0902576365" },
          { "name": "Zalo", "content": "0902576365" }
        ]
      }
    },
    {
      "images": [
        "https://pt123.cdn.static123.com/images/thumbs/900x600/fit/2023/05/12/z4339243925201-653e60ef2fa992df872a68405f41a981_1683886988.jpg",
        "https://pt123.cdn.static123.com/images/thumbs/900x600/fit/2023/05/12/z4339243933005-1ee139c36003100a092b63c2aa185d9f_1683886989.jpg",
        "https://pt123.cdn.static123.com/images/thumbs/900x600/fit/2023/05/12/z4339243909066-0fea26322d0fd18fe92fa46fb8dca4ea_1683886988.jpg",
        "https://pt123.cdn.static123.com/images/thumbs/900x600/fit/2023/05/12/z4339243918400-d92c0bb2e81da8b317e33b6199320801_1683886988.jpg",
        "https://pt123.cdn.static123.com/images/thumbs/900x600/fit/2023/05/12/z4339243925201-653e60ef2fa992df872a68405f41a981_1683886988.jpg",
        "https://pt123.cdn.static123.com/images/thumbs/900x600/fit/2023/05/12/z4339243933005-1ee139c36003100a092b63c2aa185d9f_1683886989.jpg"
      ],
      "header": {
        "title": "Chính chủ cần cho thuê nhà nguyên căn đường Nguyễn Cư Trinh, Quận 1 Gần chợ, công an phường, trường học Trần Hưng Đạo.",
        "class": {
          "content": "Chuyên mục: Cho thuê nhà Quận 1",
          "classType": "Cho thuê nhà Quận 1"
        },
        "address": "Địa chỉ: Đường Nguyễn Cư Trinh, Phường Nguyễn Cư Trinh, Quận 1, Hồ Chí Minh",
        "attributes": {
          "price": "6.5 triệu/tháng",
          "acreage": "40m2",
          "published": "18 giờ trước",
          "hashtag": "624680"
        }
      },
      "mainContent": {
        "header": "Thông tin mô tả",
        "content": [
          "Chính chủ cần cho thuê nhà nguyên căn đường Nguyễn Cư Trinh, Quận 1.",
          "Vị trí:  Gần chợ, trường học Trần Hưng Đạo và công an phường.",
          "Kiến trúc: Nhà có 1 trệt và 1 gác suốt, diện tích sử dụng là 42m2 với kích thước 3,5 x 7m. Có ban công, máy lạnh, tủ chén và các tiện nghi khác.",
          "Tiện nghi: Nhà được giữ sạch sẽ, tọa lạc trong khu vực an ninh, hẻm không sâu. Ra đường lớn có khoảng 10 căn nhà. Giờ giấc tự do, điện nước tính theo giá nhà nước.",
          "Giá thuê: 6,3 triệu/tháng (có thể thương lượng).",
          "Liên hệ:0939609011 xem nhà, nhà thực tế sạch sẽ nhà trống có máy lạnh..."
        ]
      },
      "overview": {
        "header": "Đặc điểm tin đăng",
        "content": [
          { "name": "Mã tin:", "content": "#624680" },
          { "name": "Khu vực", "content": "Cho thuê nhà Hồ Chí Minh" },
          { "name": "Loại tin rao:", "content": "Nhà thuê nguyên căn" },
          { "name": "Đối tượng thuê:", "content": "Tất cả" },
          { "name": "Gói tin:", "content": "Tin thường" },
          { "name": "Ngày đăng:", "content": "Thứ 6, 17:24 12/05/2023" },
          { "name": "Ngày hết hạn:", "content": "Thứ 4, 17:24 17/05/2023" }
        ]
      },
      "contact": {
        "header": "Thông tin liên hệ",
        "content": [
          { "name": "Liên hệ:", "content": "PKD Jamona Sacomreal" },
          { "name": "Điện thoại:", "content": "0907460261" },
          { "name": "Zalo", "content": "0907460261" }
        ]
      }
    },
    {
      "images": [
        "https://pt123.cdn.static123.com/images/thumbs/900x600/fit/2023/05/12/z4335575530911-d85f00d64d6c1a1da617839f91204b7e_1683883464.jpg",
        "https://pt123.cdn.static123.com/images/thumbs/900x600/fit/2023/05/12/z4335575514770-0948321ea2f33f06ec8300fe7c07e1a9_1683883464.jpg",
        "https://pt123.cdn.static123.com/images/thumbs/900x600/fit/2023/05/12/z4335575518470-105aec614bbaa41c217ddae4fd021b6e_1683883465.jpg",
        "https://pt123.cdn.static123.com/images/thumbs/900x600/fit/2023/05/12/z4335575543610-f717bd1cd676417a8cf7f8a3fcda9d9c_1683883462.jpg",
        "https://pt123.cdn.static123.com/images/thumbs/900x600/fit/2023/05/12/z4335575518469-a7b0cc22c13593b93d92a32d210a6a32_1683883462.jpg",
        "https://pt123.cdn.static123.com/images/thumbs/900x600/fit/2023/05/12/z4335575530911-d85f00d64d6c1a1da617839f91204b7e_1683883464.jpg",
        "https://pt123.cdn.static123.com/images/thumbs/900x600/fit/2023/05/12/z4335575514770-0948321ea2f33f06ec8300fe7c07e1a9_1683883464.jpg"
      ],
      "header": {
        "title": "Chính chủ cần cho thuê nhà nguyên căn 3PN",
        "class": {
          "content": "Chuyên mục: Cho thuê nhà Quận Thủ Đức",
          "classType": "Cho thuê nhà Quận Thủ Đức"
        },
        "address": "Địa chỉ: Đường số 3, Phường Bình Thọ, Quận Thủ Đức, Hồ Chí Minh",
        "attributes": {
          "price": "9 triệu/tháng",
          "acreage": "90m2",
          "published": "19 giờ trước",
          "hashtag": "624669"
        }
      },
      "mainContent": {
        "header": "Thông tin mô tả",
        "content": [
          "Chính chủ cần cho thuê nhà nguyên căn 3PN",
          "Địa chỉ: 39 Đường Số 3, Phường Trường Thọ, Thủ Đức, Hồ Chí Minh",
          "Diện tích: 90m²",
          "Giá cho thuê: 9 triệu/tháng.",
          "- Vị trí nhà đẹp, thoáng mát, sạch sẽ",
          "- Nhà nguyên căn có 3 phòng ngủ rộng",
          "- Thuộc khu dân cư đông đúc, dân trí cao, an ninh tốt",
          "- Giao thông đi lại rất thuận tiện, hẻm oto",
          "- Xung quanh nhiều tiện nghi",
          "Liên hệ SĐT CC: 0944527638"
        ]
      },
      "overview": {
        "header": "Đặc điểm tin đăng",
        "content": [
          { "name": "Mã tin:", "content": "#624669" },
          { "name": "Khu vực", "content": "Cho thuê nhà Hồ Chí Minh" },
          { "name": "Loại tin rao:", "content": "Nhà thuê nguyên căn" },
          { "name": "Đối tượng thuê:", "content": "Tất cả" },
          { "name": "Gói tin:", "content": "Tin thường" },
          { "name": "Ngày đăng:", "content": "Thứ 6, 16:25 12/05/2023" },
          { "name": "Ngày hết hạn:", "content": "Thứ 4, 16:25 17/05/2023" }
        ]
      },
      "contact": {
        "header": "Thông tin liên hệ",
        "content": [
          { "name": "Liên hệ:", "content": "Trịnh Hạnh" },
          { "name": "Điện thoại:", "content": "0972574779" },
          { "name": "Zalo", "content": "0972574779" }
        ]
      }
    },
    {
      "images": [
        "https://pt123.cdn.static123.com/images/thumbs/900x600/fit/2023/05/12/z3163280430781-3295647eb5fc770b53342edc89604701_1683860726.jpg",
        "https://pt123.cdn.static123.com/images/thumbs/900x600/fit/2023/05/12/z4338133038944-69aff3168bcd57b2b84d888f3eea89dd_1683860699.jpg",
        "https://pt123.cdn.static123.com/images/thumbs/900x600/fit/2023/05/12/z3163280347912-19623902f4765b40d9291b8b414fd691_1683860724.jpg",
        "https://pt123.cdn.static123.com/images/thumbs/900x600/fit/2023/05/12/z3163280429578-fd7161fdfa5004f6e08f32a8127e714d_1683860724.jpg",
        "https://pt123.cdn.static123.com/images/thumbs/900x600/fit/2023/05/12/z3163280430781-3295647eb5fc770b53342edc89604701_1683860726.jpg",
        "https://pt123.cdn.static123.com/images/thumbs/900x600/fit/2023/05/12/z4338133038944-69aff3168bcd57b2b84d888f3eea89dd_1683860699.jpg"
      ],
      "header": {
        "title": "Nhà nguyên căn hẻm xe máy,đường Nguyễn Hữu Trí, Bình Chánh.",
        "class": {
          "content": "Chuyên mục: Cho thuê nhà Huyện Bình Chánh",
          "classType": "Cho thuê nhà Huyện Bình Chánh"
        },
        "address": "Địa chỉ: E6/22A Nguyễn Hữu Trí, Thị trấn Tân Túc, Huyện Bình Chánh, Hồ Chí Minh",
        "attributes": {
          "price": "4 triệu/tháng",
          "acreage": "34m2",
          "published": "1 ngày trước",
          "hashtag": "624616"
        }
      },
      "mainContent": {
        "header": "Thông tin mô tả",
        "content": [
          "Nhà nguyên căn hẻm xe máy,đường Nguyễn Hữu Trí, Bình Chánh.",
          "+ 1 trệt , 1 lầu",
          "+ 02 phòng ngủ",
          "+ 02 vệ sinh",
          "+ Khu vực gần chợ, trung tâm huyện Bình Chánh",
          "+ Khu vực an ninh, yên tĩnh.",
          "+ Giá thuê 4 triệu,cọc trước 5 triệu."
        ]
      },
      "overview": {
        "header": "Đặc điểm tin đăng",
        "content": [
          { "name": "Mã tin:", "content": "#624616" },
          { "name": "Khu vực", "content": "Cho thuê nhà Hồ Chí Minh" },
          { "name": "Loại tin rao:", "content": "Nhà thuê nguyên căn" },
          { "name": "Đối tượng thuê:", "content": "Tất cả" },
          { "name": "Gói tin:", "content": "Tin miễn phí" },
          { "name": "Ngày đăng:", "content": "Thứ 6, 10:07 12/05/2023" },
          { "name": "Ngày hết hạn:", "content": "Thứ 4, 10:07 17/05/2023" }
        ]
      },
      "contact": {
        "header": "Thông tin liên hệ",
        "content": [
          { "name": "Liên hệ:", "content": "Minh Toàn" },
          { "name": "Điện thoại:", "content": "0377617629" },
          { "name": "Zalo", "content": "0377617629" }
        ]
      }
    },
    {
      "images": [
        "https://pt123.cdn.static123.com/images/thumbs/900x600/fit/2022/11/20/ada98580acda56840fcb_1668932991.jpg",
        "https://pt123.cdn.static123.com/images/thumbs/900x600/fit/2022/11/20/71235f1976438c1dd552_1668932991.jpg",
        "https://pt123.cdn.static123.com/images/thumbs/900x600/fit/2022/11/20/ada98580acda56840fcb_1668932991.jpg",
        "https://pt123.cdn.static123.com/images/thumbs/900x600/fit/2022/11/20/71235f1976438c1dd552_1668932991.jpg"
      ],
      "header": {
        "title": "Cho thuê nhà A6/22L Vĩnh Lộc, Vĩnh Lộc A, 3,5triệu",
        "class": {
          "content": "Chuyên mục: Cho thuê nhà Huyện Bình Chánh",
          "classType": "Cho thuê nhà Huyện Bình Chánh"
        },
        "address": "Địa chỉ: A6/22l Vĩnh Lộc, Xã Vĩnh Lộc A, Huyện Bình Chánh, Hồ Chí Minh",
        "attributes": {
          "price": "3.5 triệu/tháng",
          "acreage": "55m2",
          "published": "1 ngày trước",
          "hashtag": "610971"
        }
      },
      "mainContent": {
        "header": "Thông tin mô tả",
        "content": [
          "Chính chủ cho thuê nhà A6/22l đường Vĩnh Lộc, Ấp 1, Vĩnh Lộc A, Bình Chánh:",
          "* Mô tả chi tiết: Diện tích 4x13, nhà cấp 4, 1pn, 1pk, 1 bếp, 1 wc, nhà sạch sẽ, hẻm ô tô, khu an nình.",
          "* Vị trí: cách đường Vĩnh Lộc 100m, cách cây xăng Quang Phú 700m, đối diện UBND Vĩnh Lộc B.",
          "* Tiện ích: Gần chợ ấp 3, ần trường học, gần siêu thị, gần UBND xã",
          "* Giá thuê 3,5 triệu.",
          "* LH: anh Hùng chính chủ: 0965911733"
        ]
      },
      "overview": {
        "header": "Đặc điểm tin đăng",
        "content": [
          { "name": "Mã tin:", "content": "#610971" },
          { "name": "Khu vực", "content": "Cho thuê nhà Hồ Chí Minh" },
          { "name": "Loại tin rao:", "content": "Nhà thuê nguyên căn" },
          { "name": "Đối tượng thuê:", "content": "Tất cả" },
          { "name": "Gói tin:", "content": "Tin thường" },
          { "name": "Ngày đăng:", "content": "Thứ 5, 22:04 11/05/2023" },
          { "name": "Ngày hết hạn:", "content": "Thứ 3, 22:04 16/05/2023" }
        ]
      },
      "contact": {
        "header": "Thông tin liên hệ",
        "content": [
          { "name": "Liên hệ:", "content": "hunganh0704@yahoo.com" },
          { "name": "Điện thoại:", "content": "0965911733" },
          { "name": "Zalo", "content": "0965911733" }
        ]
      }
    },
    {
      "images": [
        "https://pt123.cdn.static123.com/images/thumbs/900x600/fit/2023/05/11/z4327292930862-8205656ca7ad9c084b26c70b93b306ba_1683796344.jpg",
        "https://pt123.cdn.static123.com/images/thumbs/900x600/fit/2023/05/11/z4327292896940-a91a4180636f64637c5ada71fb4c82d2_1683796343.jpg",
        "https://pt123.cdn.static123.com/images/thumbs/900x600/fit/2023/05/11/z4327292902125-149c34bdfbd2fa5c47aec6700749fe33_1683796343.jpg",
        "https://pt123.cdn.static123.com/images/thumbs/900x600/fit/2023/05/11/z4327292910014-fa738b3f12e001ee1897e0e7f214e65b_1683796343.jpg",
        "https://pt123.cdn.static123.com/images/thumbs/900x600/fit/2023/05/11/z4327292933228-f122b14d2e43bb6c0832ce893d4990a5_1683796344.jpg",
        "https://pt123.cdn.static123.com/images/thumbs/900x600/fit/2023/05/11/z4327292939821-3bc052a5e3013f1b97dcc68d58842114_1683796344.jpg",
        "https://pt123.cdn.static123.com/images/thumbs/900x600/fit/2023/05/11/z4327292908728-0f836393fab71fc76f72f4d090c5645d_1683796343.jpg",
        "https://pt123.cdn.static123.com/images/thumbs/900x600/fit/2023/05/11/z4327292918667-594743485c6425eb89526c6eb65a4382_1683796343.jpg",
        "https://pt123.cdn.static123.com/images/thumbs/900x600/fit/2023/05/11/z4327292919789-0c2d0099f2b6156c80802c66602359d0_1683796343.jpg",
        "https://pt123.cdn.static123.com/images/thumbs/900x600/fit/2023/05/11/z4327292930862-8205656ca7ad9c084b26c70b93b306ba_1683796344.jpg",
        "https://pt123.cdn.static123.com/images/thumbs/900x600/fit/2023/05/11/z4327292896940-a91a4180636f64637c5ada71fb4c82d2_1683796343.jpg"
      ],
      "header": {
        "title": "Cho thuê căn nhà phố liền kề Park Riverside 13tr/t full NT",
        "class": {
          "content": "Chuyên mục: Cho thuê nhà Quận 9",
          "classType": "Cho thuê nhà Quận 9"
        },
        "address": "Địa chỉ: Đường Bưng Ông Thoàn, Phường Phú Hữu, Quận 9, Hồ Chí Minh",
        "attributes": {
          "price": "13 triệu/tháng",
          "acreage": "75m2",
          "published": "1 ngày trước",
          "hashtag": "624565"
        }
      },
      "mainContent": {
        "header": "Thông tin mô tả",
        "content": [
          "Cho thuê nhà phố khu compound Park Riverside :",
          "- Thiết kế: 1 trệt, 2 lầu",
          "- Diện tích: 5x15m2",
          "- Đầy đủ nội thất tiện nghi",
          "- Giá : 13tr/t đầu tháng 6 ở được",
          "________________",
          "* Địa chỉ: SỐ 9 Bưng Ông Thoàn, P.Phú Hữu, Q.9",
          "* Tiện ích Khu hồ bơi, sân tennis, BBQ bồ sông, công viên cây xanh, bến du thuyền, khu vui chơi trẻ em, hồ sen, .....",
          "HOTLINE: 0909482961_Thuê Nhà Đẹp"
        ]
      },
      "overview": {
        "header": "Đặc điểm tin đăng",
        "content": [
          { "name": "Mã tin:", "content": "#624565" },
          { "name": "Khu vực", "content": "Cho thuê nhà Hồ Chí Minh" },
          { "name": "Loại tin rao:", "content": "Nhà thuê nguyên căn" },
          { "name": "Đối tượng thuê:", "content": "Tất cả" },
          { "name": "Gói tin:", "content": "Tin thường" },
          { "name": "Ngày đăng:", "content": "Thứ 5, 16:12 11/05/2023" },
          { "name": "Ngày hết hạn:", "content": "Thứ 3, 16:12 16/05/2023" }
        ]
      },
      "contact": {
        "header": "Thông tin liên hệ",
        "content": [
          { "name": "Liên hệ:", "content": "Thuenhadep.net" },
          { "name": "Điện thoại:", "content": "0909482961" },
          { "name": "Zalo", "content": "0909482961" },
          {
            "name": "Facebook",
            "content": "https://www.facebook.com/profile.php?id=100090947886658"
          }
        ]
      }
    },
    {
      "images": [
        "https://pt123.cdn.static123.com/images/thumbs/900x600/fit/2023/02/10/img-5407_1676009127.jpg",
        "https://pt123.cdn.static123.com/images/thumbs/900x600/fit/2023/02/10/img-5403_1676009126.jpg",
        "https://pt123.cdn.static123.com/images/thumbs/900x600/fit/2023/02/10/img-5404_1676009126.jpg",
        "https://pt123.cdn.static123.com/images/thumbs/900x600/fit/2023/02/10/img-5405_1676009126.jpg",
        "https://pt123.cdn.static123.com/images/thumbs/900x600/fit/2023/02/10/img-5406_1676009126.jpg",
        "https://pt123.cdn.static123.com/images/thumbs/900x600/fit/2023/02/10/img-5407_1676009127.jpg",
        "https://pt123.cdn.static123.com/images/thumbs/900x600/fit/2023/02/10/img-5403_1676009126.jpg"
      ],
      "header": {
        "title": "CHO THUÊ NHÀ GÒ VẤP MỚI XÂY CHƯA Ở",
        "class": {
          "content": "Chuyên mục: Cho thuê nhà Quận Gò Vấp",
          "classType": "Cho thuê nhà Quận Gò Vấp"
        },
        "address": "Địa chỉ: Đường Nguyên Hồng, Phường 1, Quận Gò Vấp, Hồ Chí Minh",
        "attributes": {
          "price": "10 triệu/tháng",
          "acreage": "75m2",
          "published": "2 ngày trước",
          "hashtag": "615759"
        }
      },
      "mainContent": {
        "header": "Thông tin mô tả",
        "content": [
          "Nhà mới xây chưa sử dụng cho thuê nguyên căn đường Nguyên Hồng ngay ngã 5 Lê Quang Định Phạm Văn Đồng, Nguyên Hồng. Nhà 1 trệt 2 lầu, mỗi lầu 1 phòng ngủ 1 toilet, trệt bếp và phòng khách, toilet đường trước nhà 3m. Phù hợp cho gia đình"
        ]
      },
      "overview": {
        "header": "Đặc điểm tin đăng",
        "content": [
          { "name": "Mã tin:", "content": "#615759" },
          { "name": "Khu vực", "content": "Cho thuê nhà Hồ Chí Minh" },
          { "name": "Loại tin rao:", "content": "Nhà thuê nguyên căn" },
          { "name": "Đối tượng thuê:", "content": "Tất cả" },
          { "name": "Gói tin:", "content": "Tin thường" },
          { "name": "Ngày đăng:", "content": "Thứ 5, 11:12 11/05/2023" },
          { "name": "Ngày hết hạn:", "content": "Thứ 3, 11:12 16/05/2023" }
        ]
      },
      "contact": {
        "header": "Thông tin liên hệ",
        "content": [
          { "name": "Liên hệ:", "content": "Thu Hoai" },
          { "name": "Điện thoại:", "content": "0903956444" },
          { "name": "Zalo", "content": "0903956444" }
        ]
      }
    },
    {
      "images": [
        "https://pt123.cdn.static123.com/images/thumbs/900x600/fit/2023/04/27/z4195707051711-c4bf05081e423fa0131d575523ac490e_1682596342.jpg",
        "https://pt123.cdn.static123.com/images/thumbs/900x600/fit/2023/04/27/cua-rao_1682596278.png",
        "https://pt123.cdn.static123.com/images/thumbs/900x600/fit/2023/04/27/z4195703484028-1eb8a7ed38b06864122faadd37b8f4a7_1682596306.jpg",
        "https://pt123.cdn.static123.com/images/thumbs/900x600/fit/2023/04/27/z4195707051711-c4bf05081e423fa0131d575523ac490e_1682596342.jpg",
        "https://pt123.cdn.static123.com/images/thumbs/900x600/fit/2023/04/27/cua-rao_1682596278.png"
      ],
      "header": {
        "title": "Nhà nguyên căn 5 triệu ( 50m2) hẻm 88 Nguyễn Văn Quỳ",
        "class": {
          "content": "Chuyên mục: Cho thuê nhà Quận 7",
          "classType": "Cho thuê nhà Quận 7"
        },
        "address": "Địa chỉ: 88/69 Đường Nguyễn Văn Quỳ, Phường Phú Thuận, Quận 7, Hồ Chí Minh",
        "attributes": {
          "price": "5 triệu/tháng",
          "acreage": "50m2",
          "published": "2 ngày trước",
          "hashtag": "623487"
        }
      },
      "mainContent": {
        "header": "Thông tin mô tả",
        "content": [
          "Tôi có 2 căn nhà nguyên căn cần cho thuê:",
          "- Địa chỉ: Hẻm 88 Nguyễn Văn Quỳ phường Phú Thuận, quận 7",
          "- Căn thứ 1: giá thuê 5 triệu tháng",
          "+ Kết cấu: 1 trệt, 1 lầu",
          "+ Diện tích sàn 4,5x7 m2 có máy lạnh",
          "- Căn thứ 2 giá 7 triệu/ tháng",
          "+ Kết cấu: 1 trệt + 1 lầu gồm 3 phòng ngủ , 1 phòng khách + bếp , 1 sân vườn để xe gắn máy, máy lạnh inverter cho phòng ngủ.",
          "+ Diện tích sàn 4,7 *10",
          "+ Cửa có khóa vân tay chống trộm",
          "+ Camera trong nhà và ngoài sân",
          "- Khách hoặc môi giới liên hệ và xem nhà sau 18g. Ban ngày tôi đi làm nên ít khi nghe máy và tiếp khách"
        ]
      },
      "overview": {
        "header": "Đặc điểm tin đăng",
        "content": [
          { "name": "Mã tin:", "content": "#623487" },
          { "name": "Khu vực", "content": "Cho thuê nhà Hồ Chí Minh" },
          { "name": "Loại tin rao:", "content": "Nhà thuê nguyên căn" },
          { "name": "Đối tượng thuê:", "content": "Tất cả" },
          { "name": "Gói tin:", "content": "Tin thường" },
          { "name": "Ngày đăng:", "content": "Thứ 5, 08:28 11/05/2023" },
          { "name": "Ngày hết hạn:", "content": "Thứ 6, 19:05 19/05/2023" }
        ]
      },
      "contact": {
        "header": "Thông tin liên hệ",
        "content": [
          { "name": "Liên hệ:", "content": "Bao Ngoc" },
          { "name": "Điện thoại:", "content": "0886233725" },
          { "name": "Zalo", "content": "0886233725" }
        ]
      }
    },
    {
      "images": [
        "https://pt123.cdn.static123.com/images/thumbs/900x600/fit/2023/02/22/c42parkriverside6_1677070664.jpg",
        "https://pt123.cdn.static123.com/images/thumbs/900x600/fit/2023/02/22/c42parkriverside2_1677070658.jpg",
        "https://pt123.cdn.static123.com/images/thumbs/900x600/fit/2023/02/22/c42parkriverside3_1677070658.jpg",
        "https://pt123.cdn.static123.com/images/thumbs/900x600/fit/2023/02/22/c42parkriverside1_1677070660.jpg",
        "https://pt123.cdn.static123.com/images/thumbs/900x600/fit/2023/02/22/c42parkriverside_1677070660.jpg",
        "https://pt123.cdn.static123.com/images/thumbs/900x600/fit/2023/02/22/c42parkriverside4_1677070662.jpg",
        "https://pt123.cdn.static123.com/images/thumbs/900x600/fit/2023/02/22/c42parkriverside5_1677070662.jpg",
        "https://pt123.cdn.static123.com/images/thumbs/900x600/fit/2023/02/22/c42parkriverside6_1677070664.jpg",
        "https://pt123.cdn.static123.com/images/thumbs/900x600/fit/2023/02/22/c42parkriverside2_1677070658.jpg"
      ],
      "header": {
        "title": "Nguyên Căn Park Riverside Q9 - Nội Thất Cơ Bản - Khu Dân Trí Cao - BV 24/7",
        "class": {
          "content": "Chuyên mục: Cho thuê nhà Quận 9",
          "classType": "Cho thuê nhà Quận 9"
        },
        "address": "Địa chỉ: Đường Bưng Ông Thoàn, Phường Phú Hữu, Quận 9, Hồ Chí Minh",
        "attributes": {
          "price": "12 triệu/tháng",
          "acreage": "75m2",
          "published": "2 ngày trước",
          "hashtag": "616988"
        }
      },
      "mainContent": {
        "header": "Thông tin mô tả",
        "content": [
          "- Nhà phố liền kề 1 trệt 2 lầu, 4 Phòng Ngủ - 3 WC",
          "- Giá thuê: 13tr/tháng. Chưa bao gồm phí quản lí (thương lượng)",
          "- Diện tích : 75m2 thiết kế hiện đại (5x15m)",
          "- Không gian thoáng mát, đường rộng thoáng, sân đậu được nhiều ô tô",
          "- Phù hợp ở hoặc làm văn phòng công ty",
          "- Nằm đối diện khu tiện ích : công viên và bờ sông thoáng mát",
          "- Chủ nhà không thích đăng hình nên anh chị quan tâm kết bạn zalo e gửi hình",
          "- Cảm ơn anh chị đã xem tin. Liên hệ xem nhà báo trước 1 giờ"
        ]
      },
      "overview": {
        "header": "Đặc điểm tin đăng",
        "content": [
          { "name": "Mã tin:", "content": "#616988" },
          { "name": "Khu vực", "content": "Cho thuê nhà Hồ Chí Minh" },
          { "name": "Loại tin rao:", "content": "Nhà thuê nguyên căn" },
          { "name": "Đối tượng thuê:", "content": "Tất cả" },
          { "name": "Gói tin:", "content": "Tin thường" },
          { "name": "Ngày đăng:", "content": "Thứ 4, 20:40 10/05/2023" },
          { "name": "Ngày hết hạn:", "content": "Thứ 2, 20:40 15/05/2023" }
        ]
      },
      "contact": {
        "header": "Thông tin liên hệ",
        "content": [
          { "name": "Liên hệ:", "content": "Anh Duy" },
          { "name": "Điện thoại:", "content": "0917998992" },
          { "name": "Zalo", "content": "0917998992" }
        ]
      }
    }
  ]
}
